iam_profile_faker/__init__.py
iam_profile_faker/cli.py
iam_profile_faker/factory.py
iam_profile_faker/schema.py
iam_profile_faker/v2_api.py
iam_profile_faker-0.3.1.dist-info/METADATA
iam_profile_faker-0.3.1.dist-info/RECORD
iam_profile_faker-0.3.1.dist-info/WHEEL
iam_profile_faker-0.3.1.dist-info/entry_points.txt
iam_profile_faker-0.3.1.dist-info/top_level.txt
