Metadata-Version: 2.1
Name: iam-profile-faker
Version: 0.3.1
Summary: Object generator based on IAM profile v2 schema
Home-page: https://github.com/mozilla-iam/iam-profile-faker
Author: John Giannelos
Author-email: johngiannelos@gmail.com
License: Apache Software License 2.0
Keywords: iam_profile_faker
Platform: UNKNOWN
Classifier: Development Status :: 2 - Pre-Alpha
Classifier: Intended Audience :: Developers
Classifier: License :: OSI Approved :: Apache Software License
Classifier: Natural Language :: English
Classifier: Programming Language :: Python :: 2
Classifier: Programming Language :: Python :: 2.7
Classifier: Programming Language :: Python :: 3
Classifier: Programming Language :: Python :: 3.4
Classifier: Programming Language :: Python :: 3.5
Classifier: Programming Language :: Python :: 3.6
Provides-Extra: api
Requires-Dist: Click (>=6.0)
Requires-Dist: Faker
Requires-Dist: tinydb
Provides-Extra: api
Requires-Dist: flask; extra == 'api'
Requires-Dist: flask-restful; extra == 'api'
Requires-Dist: flask-graphql; extra == 'api'
Requires-Dist: graphene; extra == 'api'
Requires-Dist: requests; extra == 'api'
Requires-Dist: ipdb; extra == 'api'
Requires-Dist: aniso8601; extra == 'api'
Requires-Dist: flask-cors; extra == 'api'
